iterextras/__init__.py
iterextras/lib.py
iterextras-0.2.1.dist-info/METADATA
iterextras-0.2.1.dist-info/WHEEL
iterextras-0.2.1.dist-info/top_level.txt
iterextras-0.2.1.dist-info/RECORD
